generic_collections/__init__.py
generic_collections/enums/__init__.py
generic_collections/enums/geometry_types.py
generic_collections/enums/http_methods.py
generic_collections/enums/month_periods.py
generic_collections/objects/__init__.py
generic_collections/objects/pagination.py
generic_collections/objects/point.py
generic_collections-0.1.1.dist-info/METADATA
generic_collections-0.1.1.dist-info/WHEEL
generic_collections-0.1.1.dist-info/RECORD
